Workbook
Name TOTAL: Soumission!$I$46

Sheet Soumission
I1: SOUMISSION
I2: #2026-05-05-A
A4: PAR: | B4: A/S Sylvain Pedneault | F4: À L'ATTENTION DE: | G4: A/S Claude Levert
B5: Gestion Technologies | G5: MRC de Rouville
B6: sylvain@securitepublique.ca | G6: 500, rue Desjardins, bureau 100
B7: (450) 502-9911 | G7: Marieville (Québec) J3M 1E1
A10: Détails du service
A11: La présente soumission est présentée pour l'octroi du service d'extraction des données d'une base de données Première Ligne, pour la ou les base(s) de données listées plus bas. Les inclusions à ce service sont:
A14: • Processus automatisés (non-IA): analyse, assemblage, nettoyage, adaptation, uniformisation, validation | I14: INCLUS ✔️
A15: • Deux (2) exports: 1=extraction de sûreté complète imédiate, 2=migration finale subséquente | I15: INCLUS ✔️
A16: • Lot de fichiers XML avec les données complètes structurées et normalisées | I16: INCLUS ✔️
A17: • Fichier XSD présentant le schéma de données, pour valider les fichiers XML | I17: INCLUS ✔️
A18: • Outil de consultation/recherche locale, pour navigation assistée dans les données (gratuit à vie) | I18: INCLUS ✔️
A19: • Documentation de la structure de l'export | I19: INCLUS ✔️
A20: • Option multi-SSI: données municipales dé-groupées avec données communes répétées | I20: INCLUS ✔️
A23: Bases de données | E23: Population | G23: Prix rég. | H23: Rabais | I23: Coût total (+tx)
A24: MRC Rouville (multi-services) | D24: Total: | E24: =SUM(E27:E31) -> 19457 | F24: Total: | G24: =SUM(G27:G31) -> 17000 | H24: 0.1 | I24: =G24-(G24*H24) -> 15300
B26: Municipalités | E26: Population | F26: Ratio | G26: Prix rég. | I26: Coût réparti (+tx)
B27: Ange-Gardien | E27: 3068 | F27: =E27/E$24 -> 0.15768104 | G27: =IF(E27="","",_xlfn.XLOOKUP(E27,$A$54:$A$69,$C$54:$C$69,,-1)) -> 3000 | I27: =ROUND(I$24*F27,0) -> 2413
B28: Richelieu | E28: 6070 | F28: =E28/E$24 -> 0.31196999 | G28: =IF(E28="","",_xlfn.XLOOKUP(E28,$A$54:$A$69,$C$54:$C$69,,-1)) -> 4000 | I28: =ROUND(I$24*F28,0) -> 4773
B29: Rougemont | E29: 2821 | F29: =E29/E$24 -> 0.14498638 | G29: =IF(E29="","",_xlfn.XLOOKUP(E29,$A$54:$A$69,$C$54:$C$69,,-1)) -> 3000 | I29: =ROUND(I$24*F29,0) -> 2218
B30: Saint-Mathias-sur-Richelieu | E30: 4626 | F30: =E30/E$24 -> 0.23775505 | G30: =IF(E30="","",_xlfn.XLOOKUP(E30,$A$54:$A$69,$C$54:$C$69,,-1)) -> 4000 | I30: =ROUND(I$24*F30,0) -> 3638
B31: Saint-Paul-d'Abbotsford | E31: 2872 | F31: =E31/E$24 -> 0.14760754 | G31: =IF(E31="","",_xlfn.XLOOKUP(E31,$A$54:$A$69,$C$54:$C$69,,-1)) -> 3000 | I31: =ROUND(I$24*F31,0) -> 2258
A40: Pour confirmer la commande : SVP émettre un bon de commande au nom de: Sylvain Pedneault (Gestion Technologies). Une facture sera présentée avec les données extraites, et sera payable 30 jours par chèque au nom de Sylvain Pedneault. Multi-services: si vous souhaitez que les municipalités ci-listées soient facturées individuellement pour leur coût réparti, veuillez nous faire parvenir un bon de commande par municipalité.
H46: TOTAL: | I46: =I24 -> 15300
I47: ="+taxes" -> +taxes
A51: Liste de prix
A53: POP.MIN | B53: POP.MAX | C53: PRIX
A54: 0 | B54: 4000 | C54: 3000
A55: =B54+1 -> 4001 | B55: 7500 | C55: 4000
A56: =B55+1 -> 7501 | B56: 12000 | C56: 6000
A57: =B56+1 -> 12001 | B57: 25000 | C57: 7500
A58: =B57+1 -> 25001 | B58: 50000 | C58: 12500

Sheet Prix
A7: RÉGULIER | D7: SPÉCIAL | H7: SPÉCIAL 2 | K7: SPÉCIAL 2
A9: $/unité | B9: Total | D9: $/unité | E9: Total | H9: $/unité | I9: Total | K9: $/unité | L9: Total
A10: 1 | B10: =A10*Soumission!$F27 -> 0.15768104 | D10: 1 | E10: =D10*Soumission!$F27 -> 0.15768104 | H10: 0.5 | I10: =H10*Soumission!$F27 -> 0.07884052 | K10: 0.75 | L10: =K10*Soumission!$F27 -> 0.11826078
A11: 0.05 | B11: =A11*Soumission!$F28 -> 0.015598499 | D11: 0.05 | E11: =D11*Soumission!$F28 -> 0.015598499 | H11: 0.05 | I11: =H11*Soumission!$F28 -> 0.015598499 | K11: 0.05 | L11: =K11*Soumission!$F28 -> 0.015598499
A12: 1 | B12: =A12*Soumission!$F29 -> 0.14498638 | D12: 1 | E12: =D12*Soumission!$F29 -> 0.14498638 | H12: 0.5 | I12: =H12*Soumission!$F29 -> 0.07249319 | K12: 0.75 | L12: =K12*Soumission!$F29 -> 0.10873979
A13: 1 | B13: =A13*Soumission!$F30 -> 0.23775505 | D13: 0.5 | E13: =D13*Soumission!$F30 -> 0.11887752 | H13: 0.3 | I13: =H13*Soumission!$F30 -> 0.071326515 | K13: 0.5 | L13: =K13*Soumission!$F30 -> 0.11887752
A14: 0.05 | B14: =A14*Soumission!$F31 -> 0.0073803772 | D14: 0.05 | E14: =D14*Soumission!$F31 -> 0.0073803772 | H14: 0.05 | I14: =H14*Soumission!$F31 -> 0.0073803772 | K14: 0.05 | L14: =K14*Soumission!$F31 -> 0.0073803772
A15: 1 | B15: =A15*Soumission!#REF! -> #REF! | D15: 1 | E15: =D15*Soumission!#REF! -> #REF! | H15: 0.5 | I15: =H15*Soumission!#REF! -> #REF! | K15: 0.75 | L15: =K15*Soumission!#REF! -> #REF!
A16: 1 | B16: =A16*Soumission!#REF! -> #REF! | D16: 1 | E16: =D16*Soumission!#REF! -> #REF! | H16: 0.5 | I16: =H16*Soumission!#REF! -> #REF! | K16: 0.75 | L16: =K16*Soumission!#REF! -> #REF!
A17: 1 | B17: =A17*Soumission!#REF! -> #REF! | D17: 1 | E17: =D17*Soumission!#REF! -> #REF! | H17: 0.5 | I17: =H17*Soumission!#REF! -> #REF! | K17: 0.75 | L17: =K17*Soumission!#REF! -> #REF!
A18: 1 | B18: =A18*Soumission!#REF! -> #REF! | D18: 1 | E18: =D18*Soumission!#REF! -> #REF! | H18: 0.5 | I18: =H18*Soumission!#REF! -> #REF! | K18: 0.75 | L18: =K18*Soumission!#REF! -> #REF!
A19: 1 | B19: =A19*Soumission!#REF! -> #REF! | D19: 1 | E19: =D19*Soumission!#REF! -> #REF! | H19: 0.5 | I19: =H19*Soumission!#REF! -> #REF! | K19: 0.75 | L19: =K19*Soumission!#REF! -> #REF!
A20: 1 | B20: =A20*Soumission!#REF! -> #REF! | D20: 1 | E20: =D20*Soumission!#REF! -> #REF! | H20: 0.5 | I20: =H20*Soumission!#REF! -> #REF! | K20: 0.75 | L20: =K20*Soumission!#REF! -> #REF!
A21: 1 | B21: =A21*Soumission!#REF! -> #REF! | D21: 0.5 | E21: =D21*Soumission!#REF! -> #REF! | H21: 0.3 | I21: =H21*Soumission!#REF! -> #REF! | K21: 0.5 | L21: =K21*Soumission!#REF! -> #REF!
A22: 1 | B22: =A22*Soumission!#REF! -> #REF! | D22: 1 | E22: =D22*Soumission!#REF! -> #REF! | H22: 0.5 | I22: =H22*Soumission!#REF! -> #REF! | K22: 0.75 | L22: =K22*Soumission!#REF! -> #REF!
A23: 1 | B23: =A23*Soumission!#REF! -> #REF! | D23: 0.5 | E23: =D23*Soumission!#REF! -> #REF! | H23: 0.3 | I23: =H23*Soumission!#REF! -> #REF! | K23: 0.5 | L23: =K23*Soumission!#REF! -> #REF!
A24: 1 | B24: =A24*Soumission!#REF! -> #REF! | D24: 1 | E24: =D24*Soumission!#REF! -> #REF! | H24: 0.5 | I24: =H24*Soumission!#REF! -> #REF! | K24: 0.75 | L24: =K24*Soumission!#REF! -> #REF!
A25: 1 | B25: =A25*Soumission!#REF! -> #REF! | D25: 1 | E25: =D25*Soumission!#REF! -> #REF! | H25: 0.5 | I25: =H25*Soumission!#REF! -> #REF! | K25: 0.75 | L25: =K25*Soumission!#REF! -> #REF!
A26: 1 | B26: =A26*Soumission!#REF! -> #REF! | D26: 1 | E26: =D26*Soumission!#REF! -> #REF! | H26: 0.5 | I26: =H26*Soumission!#REF! -> #REF! | K26: 0.75 | L26: =K26*Soumission!#REF! -> #REF!
... A30: 1 | B30: =A30*Soumission!#REF! -> #REF! | D30: 0.5 | E30: =D30*Soumission!#REF! -> #REF! | H30: 0.3 | I30: =H30*Soumission!#REF! -> #REF! | K30: 0.5 | L30: =K30*Soumission!#REF! -> #REF!
A31: 0.25 | B31: =A31*Soumission!$G10 -> 0 | D31: 0.25 | E31: =D31*Soumission!$G10 -> 0 | H31: 0.1 | I31: =H31*Soumission!$G10 -> 0 | K31: 0.1 | L31: =K31*Soumission!$G10 -> 0
A32: 1 | B32: =A32*Soumission!$G14 -> 0 | D32: 1 | E32: =D32*Soumission!$G14 -> 0 | H32: 0.5 | I32: =H32*Soumission!$G14 -> 0 | K32: 0.75 | L32: =K32*Soumission!$G14 -> 0
A33: 1 | B33: =A33*Soumission!$G15 -> 0 | D33: 1 | E33: =D33*Soumission!$G15 -> 0 | H33: 0.5 | I33: =H33*Soumission!$G15 -> 0 | K33: 0.75 | L33: =K33*Soumission!$G15 -> 0
A34: 0.25 | B34: =A34*Soumission!$G16 -> 0 | D34: 0.25 | E34: =D34*Soumission!$G16 -> 0 | H34: 0.1 | I34: =H34*Soumission!$G16 -> 0 | K34: 0.1 | L34: =K34*Soumission!$G16 -> 0
D37: 1 | H37: 0.5 | K37: 0.75
D38: 0.5 | H38: 0.3 | K38: 0.5
D39: 0.25 | H39: 0.1 | K39: 0.1
B47: 45181.2 | E47: 28387.7 | I47: 17044.45 | L47: 25891.85
E49: 16793.5 | I49: 11343.25 | L49: -25891.85

Sheet Données
A1: Class | B1: Général | C1: SSI Ange-Gardien | D1: SSI MRC | G1: SSI Richelieu | H1: SSI Rougemont | J1: SSI Saint-Mathias-sur-Richelieu | K1: SSI Saint-Paul-d'Abbotsford | N1: Total
A2: Configurations SSI | B2: 1 | C2: 1 | D2: 1 | G2: 1 | H2: 1 | J2: 1 | K2: 1 | M2: =SUM(B2:K2) -> 7 | N2: 10
A3: Fichiers | B3: 28356 | C3: 0 | D3: 0 | G3: 0 | H3: 0 | J3: 0 | K3: 0 | M3: =SUM(B3:K3) -> 28356 | N3: 28356
A4: Rapports central | B4: 4 | C4: 0 | D4: 0 | G4: 0 | H4: 0 | J4: 0 | K4: 0 | M4: =SUM(B4:K4) -> 4 | N4: 5
A5: Dossiers adresse | B5: 13 | C5: 2281 | D5: 0 | G5: 2895 | H5: 2206 | J5: 2328 | K5: 2086 | M5: =SUM(B5:K5) -> 11809 | N5: 20468
A6: Dossiers adresse antérieurs | B6: 3254 | C6: 3495 | D6: 0 | G6: 4236 | H6: 2856 | J6: 4259 | K6: 2833 | M6: =SUM(B6:K6) -> 20933 | N6: 28302
A7: Plans intervention | B7: 0 | C7: 88 | D7: 0 | G7: 12 | H7: 4 | J7: 41 | K7: 201 | M7: =SUM(B7:K7) -> 346 | N7: 347
A8: Documents du Plan de sécurité civile | B8: 1 | C8: 0 | D8: 0 | G8: 0 | H8: 0 | J8: 0 | K8: 1 | M8: =SUM(B8:K8) -> 2 | N8: 2
A9: Sinistres ou simulations | B9: 0 | C9: 0 | D9: 0 | G9: 0 | H9: 0 | J9: 0 | K9: 0 | M9: =SUM(B9:K9) -> 0 | N9: 0
A10: Casernes | B10: 1 | C10: 1 | D10: 1 | G10: 1 | H10: 1 | J10: 1 | K10: 1 | M10: =SUM(B10:K10) -> 7 | N10: 10
A11: Véhicules | B11: 2 | C11: 3 | D11: 0 | G11: 9 | H11: 33 | J11: 9 | K11: 6 | M11: =SUM(B11:K11) -> 62 | N11: 90
A12: Bornes | B12: 0 | C12: 0 | D12: 0 | G12: 0 | H12: 0 | J12: 1 | K12: 38 | M12: =SUM(B12:K12) -> 39 | N12: 194
A13: Maintenances de bornes | B13: 0 | C13: 0 | D13: 0 | G13: 0 | H13: 0 | J13: 0 | K13: 0 | M13: =SUM(B13:K13) -> 0 | N13: 6
... A26: Feuilles de temps (autre travail) | B26: 0 | C26: 23 | D26: 0 | G26: 0 | H26: 1 | J26: 0 | K26: 140 | M26: =SUM(B26:K26) -> 164 | N26: 2704
B28: =SUM(B2:B26) -> 33973 | C28: =SUM(C2:C26) -> 11853 | D28: =SUM(D2:D26) -> 11 | G28: =SUM(G2:G26) -> 14634 | H28: =SUM(H2:H26) -> 9475 | J28: =SUM(J2:J26) -> 12920 | K28: =SUM(K2:K26) -> 10971 | M28: =SUM(M2:M26) -> 93837 | N28: =SUM(N2:N26) -> 129536
B29: =B28/$M28 -> 0.36204269 | C29: =C28/$M28 -> 0.12631478 | G29: =G28/$M28 -> 0.15595128 | H29: =H28/$M28 -> 0.10097296 | J29: =J28/$M28 -> 0.13768556 | K29: =K28/$M28 -> 0.1169155
B30: 36 | C30: 13 | G30: 16 | H30: 10 | J30: 14 | K30: 12 | M30: =SUM(C30:K30) -> 65
C33: =Soumission!$I$46 -> 15300 | G33: =Soumission!$I$46 -> 15300 | H33: =Soumission!$I$46 -> 15300 | J33: =Soumission!$I$46 -> 15300 | K33: =Soumission!$I$46 -> 15300
C34: =C33*(C29+($B$29/5)) -> 3040.4668 | G34: =G33*(G29+($B$29/5)) -> 3493.9052 | H34: =H33*(H29+($B$29/5)) -> 2652.737 | J34: =J33*(J29+($B$29/5)) -> 3214.4397 | K34: =K33*(K29+($B$29/5)) -> 2896.6578 | M34: =SUM(B34:K34) -> 15298.206
C35: 5145 | G35: 5912 | H35: 4489 | J35: 5439 | K35: 4901 | M35: =SUM(B35:K35) -> 25886
